{
  "ciclo": "2026-1",
  "drive": "https://drive.google.com/drive/folders/1kfYSpxqiZplSyIpZMnHb2nAFNRRRr77y?usp=sharing",
  "profesor": "Arsenio Muñoz",
  "area": "Humanidades",
  "descripcion": "Un curso que te hará cuestionar más de una certeza. Entre dilemas, empresas y decisiones difíciles, aprenderás que hacer negocios también implica elegir qué tipo de profesional (y persona) quieres ser.",
  "icono": "gavel",
  "tips": [
    "El profe te hace participar en clase. Revisa los AS.",
    "El control de lectura es para marcar y con laptop abierto."
  ],
  "titulo": "Ética y Negocios",
  "universidad": "Universidad del Pacífico - MBA"
}
