{
  "ciclo": "2020-2",
  "drive": "https://drive.google.com/drive/folders/1h7r6iJl_3Q6ndtk2zx1pn52weH5jKub0?usp=drive_link",
  "profesor": "Rosa Elvira Vargas",
  "area": "Humanidades",
  "descripcion": "¿Cuánto hemos estado frente a un dilema ético en la vida laboral/personal?",
  "icono": "heart",
  "tips": [
    "Sigue una misma estructura de redacción para el parcial y el final",
    "Pregunta cómo aplicar las teorías éticas a casos concretos.",
    "Las lecturas de AS tiene resaltado las partes importantes."
  ],
  "titulo": "Ética",
  "universidad": "Universidad del Pacífico"
}
