{
  "ciclo": "2015-1",
  "color": "#D97706",
  "drive": "https://drive.google.com/drive/folders/0B9GJusvT-N-TVDNDQkUzQ1RJZHc?resourcekey=0-9pc0ouscQyXhQWj4Ah-YBw&usp=sharing",
  "profesor": "Carlos Zelada",
  "area": "Derecho",
  "icono": null,
  "tips": [
    "Lee el libro Introducción al Derecho de Marcial Rubio. Casi toda la primera parte del curso se basa en el libro.",
    "La clase de desagregación de normas es vital para tu vida. No faltes.",
    "Sé claro a la hora de redactar. ¡No florees!"
  ],
  "titulo": "Introducción al Derecho",
  "universidad": "Universidad del Pacífico"
}
